{
    "securityId": "-ksrpooHqmOCN-M1ODqDMYAMu9kbYltmN3gCJWFbXdtsbEvUBw_AnGLH38QwLBt3oykED3m_22uBy7kmOuirYY2AHltv0sY0wcMuLEj8cj6srbC2IQ~~",
    "bossAvatar": "https://img.bosszhipin.com/beijin/upload/avatar/20200625/46a9334d14d071155c62e5b92f57ec9cc1dc6fbd251d8cf7b26137de708c5160_s.jpg",
    "bossCert": 3,
    "encryptBossId": "2be04536915689860nd_3dq_EVU~",
    "bossName": "刘女士",
    "bossTitle": "HR",
    "goldHunter": 0,
    "bossOnline": false,
    "encryptJobId": "8ae5127a7273b17e1HN_2Nu9GFJX",
    "expectId": 0,
    "jobName": "数据处理工程师（2025届）",
    "lid": "3pZfrtkwdSl.search.298",
    "salaryDesc": "6-10K",
    "jobLabels": [
        "在校/应届",
        "本科"
    ],
    "jobValidStatus": 1,
    "iconWord": "",
    "skills": [
        "熟练使用测绘类型软件",
        "会点云数据处理",
        "测绘遥感地信"
    ],
    "jobExperience": "在校/应届",
    "daysPerWeekDesc": "",
    "leastMonthDesc": "",
    "jobDegree": "本科",
    "cityName": "武汉",
    "areaDistrict": "洪山区",
    "businessDistrict": "花山",
    "jobType": 5,
    "proxyJob": 0,
    "proxyType": 0,
    "anonymous": 0,
    "outland": 0,
    "optimal": 0,
    "iconFlagList": [],
    "itemId": 298,
    "city": 101200100,
    "isShield": 0,
    "atsDirectPost": false,
    "gps": {
        "longitude": 114.508459,
        "latitude": 30.54948
    },
    "encryptBrandId": "78b9ce60fc5cc1af1XR50t6-FQ~~",
    "brandName": "数字绿土",
    "brandLogo": "https://img.bosszhipin.com/beijin/mcs/chatphoto/20190906/0d44382aa62052f04e1cb14618a7c31f860e745e36e2ae0f782791482bac5813_s.jpg",
    "brandStageName": "D轮及以上",
    "brandIndustry": "专用设备",
    "brandScaleName": "500-999人",
    "welfareList": [
        "绩效奖金",
        "交通补助",
        "团建聚餐",
        "定期体检",
        "生日福利",
        "带薪年假",
        "员工旅游",
        "股票期权",
        "通讯补贴",
        "节日福利",
        "年终奖",
        "零食下午茶",
        "补充医疗保险",
        "五险一金"
    ],
    "industry": 100907,
    "contact": false,
    "showTopPosition": false
}