{
    "securityId": "TUSAnb_Ed6MIY-41FQjkBmyXY4mM9gzcGDT2COeKZBfcprFzFgfivPaOv_K_CF5mCLE7-7gKRdH1SmLbAzeAzA_O8kc2N7NLp86grL0XIuF0lXmx1G3eAHvVY1AVmm5oD4P8_hK-8Rq_HsU~",
    "bossAvatar": "https://img.bosszhipin.com/boss/avatar/avatar_9.png",
    "bossCert": 3,
    "encryptBossId": "c38e99af272403170nZy3tm_EVdQ",
    "bossName": "罗女士",
    "bossTitle": "HR",
    "goldHunter": 0,
    "bossOnline": false,
    "encryptJobId": "55b6669951e0f9421HNz39S9F1RQ",
    "expectId": 1030426395,
    "jobName": "采集运维",
    "lid": "aThmQoxNFOp.search.254",
    "salaryDesc": "4-6K",
    "jobLabels": [
        "1-3年",
        "大专"
    ],
    "jobValidStatus": 1,
    "iconWord": "",
    "skills": [
        "采集运维",
        "国网"
    ],
    "jobExperience": "1-3年",
    "daysPerWeekDesc": "",
    "leastMonthDesc": "",
    "jobDegree": "大专",
    "cityName": "德阳",
    "areaDistrict": "旌阳区",
    "businessDistrict": "珠江西路",
    "jobType": 0,
    "proxyJob": 0,
    "proxyType": 0,
    "anonymous": 0,
    "outland": 0,
    "optimal": 0,
    "iconFlagList": [],
    "itemId": 254,
    "city": 101271700,
    "isShield": 0,
    "atsDirectPost": false,
    "gps": null,
    "encryptBrandId": "e5e52e8b728c4d2c1XN92t25E1Y~",
    "brandName": "森普达能源",
    "brandLogo": "https://img.bosszhipin.com/beijin/upload/com/logo/20230528/7b5b554d84f9729ced9fcdf38160c9272afa58c104160e436a6ecd28c11f7f366bb8b3da8a6c2b49.png",
    "brandStageName": "未融资",
    "brandIndustry": "电力/热力/燃气/水利",
    "brandScaleName": "100-499人",
    "welfareList": [
        "保底工资",
        "夜班补助",
        "免费工装",
        "通讯补贴",
        "底薪加提成",
        "生日福利",
        "意外险",
        "节日福利",
        "包住",
        "补充医疗保险",
        "带薪年假",
        "宿舍有空调",
        "住房补贴",
        "定期体检",
        "五险一金",
        "团建聚餐",
        "年终奖",
        "加班补助",
        "交通补助",
        "节假日加班费"
    ],
    "industry": 101205,
    "contact": false,
    "showTopPosition": false
}