{
    "securityId": "GZW00xQbLW-QX-a1wZI1hJnKO_YrFM26-1EWlRm1lk243u0e5aOoEl5FXE2c5ONEl6jXmtb58oZrSen81qdUULdW0ODp0of8k4aKy11wqkYgF-aEe4px",
    "bossAvatar": "https://img.bosszhipin.com/boss/avatar/avatar_8.png",
    "bossCert": 3,
    "encryptBossId": "fa2bb1ca68f290b50XFz39-1GVJX",
    "bossName": "曹家文",
    "bossTitle": "项目总监",
    "goldHunter": 0,
    "bossOnline": false,
    "encryptJobId": "dfbdfb4931c75d0a1HN63du0GFFU",
    "expectId": 0,
    "jobName": "AGV系统实施工程师",
    "lid": "1iHBo11mFzY.search.140",
    "salaryDesc": "4-6K",
    "jobLabels": [
        "经验不限",
        "本科"
    ],
    "jobValidStatus": 1,
    "iconWord": "",
    "skills": [
        "计算机相关专业",
        "可适应出差"
    ],
    "jobExperience": "经验不限",
    "daysPerWeekDesc": "",
    "leastMonthDesc": "",
    "jobDegree": "本科",
    "cityName": "杭州",
    "areaDistrict": "临安区",
    "businessDistrict": "青山",
    "jobType": 0,
    "proxyJob": 0,
    "proxyType": 0,
    "anonymous": 0,
    "outland": 0,
    "optimal": 0,
    "iconFlagList": [],
    "itemId": 140,
    "city": 101210100,
    "isShield": 0,
    "atsDirectPost": false,
    "gps": null,
    "encryptBrandId": "e03a9c3c8d7247281n1729y-F1c~",
    "brandName": "时铁科技",
    "brandLogo": "https://img.bosszhipin.com/beijin/upload/com/logo/20210912/7b5b554d84f9729c7fb38b3d1fff8dfd66eb94bc054a872df07b9b762d987ec10b503e901ab739fd.jpg",
    "brandStageName": "不需要融资",
    "brandIndustry": "计算机软件",
    "brandScaleName": "20-99人",
    "welfareList": [
        "股票期权",
        "带薪年假",
        "零食下午茶",
        "缴纳五险"
    ],
    "industry": 100021,
    "contact": false,
    "showTopPosition": false
}