{
    "securityId": "BK_9_ljiPoZPh-Q1lJLs77oqRC4UNEBmrmCQrv_6hC4qAeuJF1BP6jeJ9Geupejx7KvTED3HOVSjwyo_hCxm22lYINAWjDDD0cw55Yt4Sx_C_W0~",
    "bossAvatar": "https://img.bosszhipin.com/beijin/mcs/useravatar/20190310/c8550f766fb5b3a7ffaa39e9e1e0dbfc4f7d48f049f6b5491c5316f58c814a36_s.jpg",
    "bossCert": 3,
    "encryptBossId": "0ca257abd39ca24a0nJ93ty4EVA~",
    "bossName": "裘先生",
    "bossTitle": "监理员",
    "goldHunter": 0,
    "bossOnline": false,
    "encryptJobId": "bc4baf55f0478ae10HV60tu4EFI~",
    "expectId": 0,
    "jobName": "通信监理员",
    "lid": "aoxsGz4ftpb.search.163",
    "salaryDesc": "4-5K",
    "jobLabels": [
        "1-3年",
        "大专"
    ],
    "jobValidStatus": 1,
    "iconWord": "",
    "skills": [
        "移动通信",
        "无线通信",
        "数据通信",
        "有线传输",
        "项目管理",
        "项目实施",
        "通信工程师",
        "通信"
    ],
    "jobExperience": "1-3年",
    "daysPerWeekDesc": "",
    "leastMonthDesc": "",
    "jobDegree": "大专",
    "cityName": "杭州",
    "areaDistrict": "拱墅区",
    "businessDistrict": "上塘",
    "jobType": 0,
    "proxyJob": 0,
    "proxyType": 0,
    "anonymous": 0,
    "outland": 0,
    "optimal": 0,
    "iconFlagList": [],
    "itemId": 163,
    "city": 101210100,
    "isShield": 0,
    "atsDirectPost": false,
    "gps": null,
    "encryptBrandId": "d50c109e508689ea1X1809i9",
    "brandName": "公诚",
    "brandLogo": "https://img.bosszhipin.com/beijin/mcs/chatphoto/20180919/e2746a91e7ad0d85ff6fe53a5f43df5556718f074d0c65f3d075a8af4fd65123.jpg",
    "brandStageName": "已上市",
    "brandIndustry": "通信/网络设备",
    "brandScaleName": "1000-9999人",
    "welfareList": [
        "住房补贴",
        "五险一金",
        "加班补助",
        "节日福利",
        "定期体检",
        "全勤奖",
        "年终奖",
        "通讯补贴",
        "补充医疗保险",
        "餐补",
        "带薪年假",
        "交通补助"
    ],
    "industry": 100024,
    "contact": false,
    "showTopPosition": false
}