{
    "securityId": "ZkH7gewo_zrIh-c1xRss24yt2Ps1aSRVL9KfVFr-HCNhgJfhCK0Yw8SrECIhkbzVknT9YEe52nlxwqzdOaWKC75z2NLUKq8aVWn6WPbr7h0z2D38tQ~~",
    "bossAvatar": "https://img.bosszhipin.com/beijin/mcs/useravatar/20181212/ee350e1590bb1286823b0c892c386a5a74371033910f906539ff79e9480bac00_s.jpg",
    "bossCert": 3,
    "encryptBossId": "4176e7b0995e30931XJ529W-FlA~",
    "bossName": "林淑琴",
    "bossTitle": "招聘者",
    "goldHunter": 0,
    "bossOnline": false,
    "encryptJobId": "e064c8511e79bfc91HBy39u8E1NQ",
    "expectId": 0,
    "jobName": "软件项目管理专员",
    "lid": "7WBJ25gFX6N.search.56",
    "salaryDesc": "7-12K",
    "jobLabels": [
        "1-3年",
        "本科"
    ],
    "jobValidStatus": 1,
    "iconWord": "",
    "skills": [
        "项目跟进"
    ],
    "jobExperience": "1-3年",
    "daysPerWeekDesc": "",
    "leastMonthDesc": "",
    "jobDegree": "本科",
    "cityName": "厦门",
    "areaDistrict": "湖里区",
    "businessDistrict": "湖里大道",
    "jobType": 0,
    "proxyJob": 0,
    "proxyType": 0,
    "anonymous": 0,
    "outland": 0,
    "optimal": 0,
    "iconFlagList": [],
    "itemId": 56,
    "city": 101230200,
    "isShield": 0,
    "atsDirectPost": false,
    "gps": null,
    "encryptBrandId": "8102b01bdef5de2c1XR729S5Ew~~",
    "brandName": "思泰克智能",
    "brandLogo": "https://img.bosszhipin.com/beijin/mcs/chatphoto/20180531/d9e9463c5602138bb45cd5472b459c67cfcd208495d565ef66e7dff9f98764da.jpg",
    "brandStageName": "已上市",
    "brandIndustry": "自动化设备",
    "brandScaleName": "100-499人",
    "welfareList": [
        "年终奖",
        "定期体检",
        "带薪年假",
        "五险一金"
    ],
    "industry": 100914,
    "contact": false,
    "showTopPosition": false
}