{
    "securityId": "NZd0-FE55e_55-s11A_EL37h8KgOnWzp3a34wFtcyggOmZOCDB5aH__Spg3WJMrb07dBvXUYQ2vaLs1RBAex6S1VgRXrPx5_nV_IcCLIHw71JysTlA_EybWhqc-mjMydScWsdopYMyACAO-NTCUCrT9t3htJ95QZLXQMwJaEflzBDf34WjY~",
    "bossAvatar": "https://img.bosszhipin.com/beijin/upload/avatar/20240731/607f1f3d68754fd03c7ba8d1c46c5cd107098fbcd9c98ec4714bf6b6afa3e2747cb6d0de264dbf22_s.png.webp",
    "bossCert": 3,
    "encryptBossId": "83d7c23bb9a9e5490XF52Nm4F1RQ",
    "bossName": "李女士",
    "bossTitle": "HR",
    "goldHunter": 0,
    "bossOnline": true,
    "encryptJobId": "2d59f5674b2e44541HN-3tS1E1pQ",
    "expectId": 1014042683,
    "jobName": "方位招聘质量管理/测试",
    "lid": "73c7LCEYZYA.search.234",
    "salaryDesc": "4-6K",
    "jobLabels": [
        "经验不限",
        "大专"
    ],
    "jobValidStatus": 1,
    "iconWord": "",
    "skills": [
        "文员"
    ],
    "jobExperience": "经验不限",
    "daysPerWeekDesc": "",
    "leastMonthDesc": "",
    "jobDegree": "大专",
    "cityName": "苏州",
    "areaDistrict": "吴中区",
    "businessDistrict": "木渎",
    "jobType": 0,
    "proxyJob": 0,
    "proxyType": 0,
    "anonymous": 0,
    "outland": 0,
    "optimal": 0,
    "iconFlagList": [],
    "itemId": 234,
    "city": 101190400,
    "isShield": 0,
    "atsDirectPost": false,
    "gps": null,
    "encryptBrandId": "8d71633f545a2a621nZ639-8EFo~",
    "brandName": "方位",
    "brandLogo": "https://img.bosszhipin.com/beijin/upload/com/logo/20200925/a42afb250307d8cadc6545b1cb94d1198495e819ea7eecad9b6303e73616e82c.png",
    "brandStageName": "不需要融资",
    "brandIndustry": "医疗器械",
    "brandScaleName": "20-99人",
    "welfareList": [
        "五险一金",
        "定期体检"
    ],
    "industry": 100403,
    "contact": false,
    "showTopPosition": false
}