{
    "securityId": "btcIDbV3llBBJ-E1LwMcg27T3C7bMjwKHJBKVe797cDToEn87tu21zR983l_oWybnHC4gC6N1c5KRHEUcL1QktM2VWKyzN3K4T06qIaBj6Ll44TO",
    "bossAvatar": "https://img.bosszhipin.com/beijin/upload/avatar/20210411/f55068219354ef6c48f55a1dcfc6972ff7e4cdd0f86169daba3a9fbdc946d70f_s.jpg",
    "bossCert": 3,
    "encryptBossId": "0e20bbb8333dc9d13nJy3Ni_Flo~",
    "bossName": "邬先生",
    "bossTitle": "hr",
    "goldHunter": 0,
    "bossOnline": false,
    "encryptJobId": "29078c8b73078f551nZ43di7EFVT",
    "expectId": 0,
    "jobName": "软件开发工程师",
    "lid": "5JkaJXaKZhV.search.13",
    "salaryDesc": "1-2K·16薪",
    "jobLabels": [
        "在校/应届",
        "本科"
    ],
    "jobValidStatus": 1,
    "iconWord": "",
    "skills": [
        "分布式技术",
        "架构师",
        "计算机软件",
        "IT服务"
    ],
    "jobExperience": "在校/应届",
    "daysPerWeekDesc": "",
    "leastMonthDesc": "",
    "jobDegree": "本科",
    "cityName": "深圳",
    "areaDistrict": "龙岗区",
    "businessDistrict": "坂田",
    "jobType": 5,
    "proxyJob": 0,
    "proxyType": 0,
    "anonymous": 0,
    "outland": 0,
    "optimal": 0,
    "iconFlagList": [],
    "itemId": 13,
    "city": 101280600,
    "isShield": 0,
    "atsDirectPost": false,
    "gps": {
        "longitude": 114.059803,
        "latitude": 22.650574
    },
    "encryptBrandId": "21124e51a5ea83a80nR80ti8",
    "brandName": "华为技术有限公司",
    "brandLogo": "https://img.bosszhipin.com/beijin/mcs/chatphoto/20170407/e6a14e190f467455f48c850ec835ec290b8e4144bb3cfe0ff348c95cc876b511.jpg",
    "brandStageName": "不需要融资",
    "brandIndustry": "计算机软件",
    "brandScaleName": "10000人以上",
    "welfareList": [
        "年终奖",
        "通讯补贴",
        "补充医疗保险",
        "股票期权",
        "交通补助",
        "五险一金",
        "免费班车",
        "节日福利",
        "餐补",
        "加班补助",
        "带薪年假",
        "定期体检",
        "全勤奖",
        "零食下午茶",
        "住房补贴",
        "员工旅游",
        "离职补偿"
    ],
    "industry": 100021,
    "contact": false,
    "showTopPosition": false
}