{
    "securityId": "Dv7aezTIvuXGd-i1VGxqQkvjXzSQQWOt3AhnNBLNRQokEYhpUj67o7GhtYu4B2rxPzlD3OJ0HiW6dqfbf8zgdiwrQWBpo379hRhb9T5Ye3vHBrRuS5Pk",
    "bossAvatar": "https://img.bosszhipin.com/beijin/upload/avatar/20201014/87075606c8bb3d46d70b756520b31cb7e64a6f330118a0462ecb1e7f1c94432d_s.png",
    "bossCert": 3,
    "encryptBossId": "80b48dcf85b4d94e0nR72du4GVVW",
    "bossName": "张先生",
    "bossTitle": "经理\t",
    "goldHunter": 0,
    "bossOnline": false,
    "encryptJobId": "0fade0a23d9bab751nR_2N-4GVVR",
    "expectId": 0,
    "jobName": "电子信息工程实习生、大数据分析",
    "lid": "aKO7393PX34.search.143",
    "salaryDesc": "6-8K",
    "jobLabels": [
        "经验不限",
        "大专"
    ],
    "jobValidStatus": 1,
    "iconWord": "",
    "skills": [
        "数据分析"
    ],
    "jobExperience": "经验不限",
    "daysPerWeekDesc": "",
    "leastMonthDesc": "",
    "jobDegree": "大专",
    "cityName": "北京",
    "areaDistrict": "丰台区",
    "businessDistrict": "科技园区",
    "jobType": 0,
    "proxyJob": 0,
    "proxyType": 0,
    "anonymous": 0,
    "outland": 0,
    "optimal": 0,
    "iconFlagList": [],
    "itemId": 143,
    "city": 101010100,
    "isShield": 0,
    "atsDirectPost": false,
    "gps": null,
    "encryptBrandId": "070745eb999976f01nVy2N66Flo~",
    "brandName": "鑫多多网络",
    "brandLogo": "https://img.bosszhipin.com/beijin/app/mobile/normal-0e3f1e4441a21d4874cece3a3d81f0fe.png",
    "brandStageName": "",
    "brandIndustry": "互联网",
    "brandScaleName": "20-99人",
    "welfareList": [],
    "industry": 100020,
    "contact": false,
    "showTopPosition": false
}