{
    "securityId": "eXb6Bj5BFIV4q-h10nKGflGAPJR9vlJEgiwSdU2UMx-SHI9jCqpvaqycoSNC0Sa0JVrlFOgSLv7Sw_wdYp6Qtyh6dEZZHAubJUWrLA7X5dzoh7kQKv0~",
    "bossAvatar": "https://img.bosszhipin.com/boss/avatar/avatar_3.png",
    "bossCert": 3,
    "encryptBossId": "c72710c636dc5eb91nZ72dS5F1NT",
    "bossName": "童女士",
    "bossTitle": "HR",
    "goldHunter": 0,
    "bossOnline": false,
    "encryptJobId": "bc66e2013530c1a51HV80tW5FFFZ",
    "expectId": 0,
    "jobName": "软件开发工程师",
    "lid": "EEatTqnohJ.search.145",
    "salaryDesc": "6-10K",
    "jobLabels": [
        "1-3年",
        "本科"
    ],
    "jobValidStatus": 1,
    "iconWord": "",
    "skills": [
        "C++",
        "C#",
        "C#开发经验",
        "应用层开发"
    ],
    "jobExperience": "1-3年",
    "daysPerWeekDesc": "",
    "leastMonthDesc": "",
    "jobDegree": "本科",
    "cityName": "成都",
    "areaDistrict": "双流区",
    "businessDistrict": "成都高新区",
    "jobType": 0,
    "proxyJob": 0,
    "proxyType": 0,
    "anonymous": 0,
    "outland": 0,
    "optimal": 0,
    "iconFlagList": [],
    "itemId": 145,
    "city": 101270100,
    "isShield": 0,
    "atsDirectPost": false,
    "gps": null,
    "encryptBrandId": "36fd17fcd3fcb4a51XJz0tW9Eg~~",
    "brandName": "乐创技术",
    "brandLogo": "https://img.bosszhipin.com/beijin/upload/com/workfeel/20231026/7bf6f160950405e9c25e2858a98747a355dfa37d4bda8848bed983402e91efaa2ab0ceba93debc04.png.webp",
    "brandStageName": "不需要融资",
    "brandIndustry": "计算机软件",
    "brandScaleName": "100-499人",
    "welfareList": [
        "意外险",
        "年终奖",
        "股票期权",
        "通讯补贴",
        "五险一金",
        "团建聚餐",
        "员工旅游",
        "交通补助",
        "定期体检",
        "带薪年假"
    ],
    "industry": 100021,
    "contact": false,
    "showTopPosition": false
}