{
    "securityId": "qHQSpJt2KZH7V-g1GhzG1jaieDUFsUtHEQ_T7LMXPK5KV2FwRyzAl9ZdoGIlvItuDOeiGJ442cJt4Il9vUmWVFdU_MTdFf0B_cZnYgaAUSwOA8VMJrOcPhjCN48lMJeLKGh0hP_AWixbYoo~",
    "bossAvatar": "https://img.bosszhipin.com/boss/avatar/avatar_12.png",
    "bossCert": 3,
    "encryptBossId": "689d8ea8aa4310dc0XR72NS0ElpV",
    "bossName": "应春丽",
    "bossTitle": "HR",
    "goldHunter": 0,
    "bossOnline": false,
    "encryptJobId": "7f8c324f46681f601Hxy09u1E1pT",
    "expectId": 1014042683,
    "jobName": "销售内勤专员",
    "lid": "2gTRTCBa7m1.search.190",
    "salaryDesc": "4-6K",
    "jobLabels": [
        "1年以内",
        "大专"
    ],
    "jobValidStatus": 1,
    "iconWord": "",
    "skills": [
        "批发/零售",
        "数据分析能力",
        "服务意识",
        "沟通能力",
        "企业（To B）",
        "协调出库与物流",
        "配合处理售后",
        "销售数据统计分析",
        "基本坐班",
        "对机构（To B）销售经验",
        "销售助理/运营相关工作经验",
        "市场推广经验",
        "门店/柜台销售",
        "网络销售"
    ],
    "jobExperience": "1年以内",
    "daysPerWeekDesc": "",
    "leastMonthDesc": "",
    "jobDegree": "大专",
    "cityName": "杭州",
    "areaDistrict": "余杭区",
    "businessDistrict": "闲林",
    "jobType": 0,
    "proxyJob": 0,
    "proxyType": 0,
    "anonymous": 0,
    "outland": 0,
    "optimal": 0,
    "iconFlagList": [],
    "itemId": 190,
    "city": 101210100,
    "isShield": 0,
    "atsDirectPost": false,
    "gps": null,
    "encryptBrandId": "399640e06633ad081HJ63di5FlM~",
    "brandName": "爱维因健康",
    "brandLogo": "https://img.bosszhipin.com/beijin/icon/894ce6fa7e58d64d57e7f22d2f3a9d18afa7fcceaa24b8ea28f56f1bb14732c0.png",
    "brandStageName": "",
    "brandIndustry": "批发/零售",
    "brandScaleName": "20-99人",
    "welfareList": [],
    "industry": 101011,
    "contact": false,
    "showTopPosition": false
}