{
    "securityId": "GC8XV5srmVRpG--1dY1-H7BzdVz9xWvZJp5twASBBbYg1dhbCga2qSoFs1_bzCk19JXEP9YABUceqmOs46GpbSq4Qg6qqte-vAZm_ta__0Ljhhs~",
    "bossAvatar": "https://img.bosszhipin.com/boss/avatar/avatar_14.png",
    "bossCert": 3,
    "encryptBossId": "be7950b5263625421nRz3Nq4EVtR",
    "bossName": "覃先生",
    "bossTitle": "测试经理",
    "goldHunter": 0,
    "bossOnline": false,
    "encryptJobId": "9eae94faf4f559f71XF62ty-FVZT",
    "expectId": 0,
    "jobName": "测试开发",
    "lid": "ShFBX7GqSy.search.45",
    "salaryDesc": "15-30K",
    "jobLabels": [
        "经验不限",
        "本科"
    ],
    "jobValidStatus": 1,
    "iconWord": "",
    "skills": [
        "自动化测试",
        "Java",
        "Selenium",
        "Shell",
        "自动化测试经验",
        "测试工作经验"
    ],
    "jobExperience": "经验不限",
    "daysPerWeekDesc": "",
    "leastMonthDesc": "",
    "jobDegree": "本科",
    "cityName": "长沙",
    "areaDistrict": "岳麓区",
    "businessDistrict": "麓谷",
    "jobType": 0,
    "proxyJob": 0,
    "proxyType": 0,
    "anonymous": 0,
    "outland": 0,
    "optimal": 0,
    "iconFlagList": [],
    "itemId": 45,
    "city": 101250100,
    "isShield": 0,
    "atsDirectPost": false,
    "gps": null,
    "encryptBrandId": "02cd05cce753437e33V50w~~",
    "brandName": "华为",
    "brandLogo": "https://img.bosszhipin.com/beijin/upload/com/logo/20200429/8f64c9d0b30a53c434b26799ca78966cec9b49ecaf1604cb263748f03d5c2b0f.png",
    "brandStageName": "不需要融资",
    "brandIndustry": "计算机软件",
    "brandScaleName": "10000人以上",
    "welfareList": [
        "加班补助",
        "员工旅游",
        "补充医疗保险",
        "餐补",
        "定期体检",
        "股票期权",
        "年终奖",
        "零食下午茶",
        "节日福利",
        "五险一金"
    ],
    "industry": 100021,
    "contact": false,
    "showTopPosition": false
}