{
    "securityId": "dHWKplmQx63bd-w1UWGVwnXx6igwXJPyMzAy91tn547Y1SMdXpCpJ9YnwPBUSIxy3rhbc6Ih9JDsANmkJlcbinamkf2OIxgJkiAe1-yy5wDuGJSPEyCH",
    "bossAvatar": "https://img.bosszhipin.com/beijin/upload/avatar/20240612/607f1f3d68754fd084f98a35aa56a3aaa1479f08480fe78ff4ba42f2481420f7870f1ca097d97e38_s.png.webp",
    "bossCert": 3,
    "encryptBossId": "56859fb74ec9ae730nZ_29-0F1pS",
    "bossName": "石先生",
    "bossTitle": "经理",
    "goldHunter": 0,
    "bossOnline": false,
    "encryptJobId": "8fd80d05b10f32da1HJ5092_E1tY",
    "expectId": 0,
    "jobName": "跨境电商运营专员",
    "lid": "1DPLNBCgdiO.search.151",
    "salaryDesc": "4-9K",
    "jobLabels": [
        "1-3年",
        "大专"
    ],
    "jobValidStatus": 1,
    "iconWord": "",
    "skills": [],
    "jobExperience": "1-3年",
    "daysPerWeekDesc": "",
    "leastMonthDesc": "",
    "jobDegree": "大专",
    "cityName": "杭州",
    "areaDistrict": "上城区",
    "businessDistrict": "九堡",
    "jobType": 0,
    "proxyJob": 0,
    "proxyType": 0,
    "anonymous": 0,
    "outland": 0,
    "optimal": 0,
    "iconFlagList": [],
    "itemId": 151,
    "city": 101210100,
    "isShield": 0,
    "atsDirectPost": false,
    "gps": {
        "longitude": 120.262692,
        "latitude": 30.308462
    },
    "encryptBrandId": "c80c66d393b0d9391HF-3tq-F1Y~",
    "brandName": "杭州香耐科技有限公司",
    "brandLogo": "https://img.bosszhipin.com/beijin/icon/894ce6fa7e58d64d57e7f22d2f3a9d18afa7fcceaa24b8ea28f56f1bb14732c0.png",
    "brandStageName": "",
    "brandIndustry": "电子商务",
    "brandScaleName": "20-99人",
    "welfareList": [
        "节日福利",
        "底薪加提成",
        "五险一金"
    ],
    "industry": 100001,
    "contact": false,
    "showTopPosition": false
}