{
    "securityId": "rbn4HVzw66wA0-v1bUSBjlIXumtGwEZH7py9YeR5gIWcR3CyHz0AOwR6W-P-3HSJqptN2or1u6s1zriD0ym8sdAfkHXHkUJow1MtC70wa5ZXjct0XF8~",
    "bossAvatar": "https://img.bosszhipin.com/beijin/upload/avatar/20230727/607f1f3d68754fd04e1e1a7a7da75f1fae03e5990d70d80f7e158fc6392973cdb7bb60f69ff68b81_s.png.webp",
    "bossCert": 3,
    "encryptBossId": "d25d5ccbda370d770XV43d-8EFNU",
    "bossName": "程先生",
    "bossTitle": "鸿蒙开发者支持负责人",
    "goldHunter": 0,
    "bossOnline": false,
    "encryptJobId": "688b09c1c7ed9d4e1HR_2dW9ElNS",
    "expectId": 0,
    "jobName": "Java",
    "lid": "Fvujp5KmUA.search.50",
    "salaryDesc": "20-40K",
    "jobLabels": [
        "经验不限",
        "本科"
    ],
    "jobValidStatus": 1,
    "iconWord": "",
    "skills": [
        "Java",
        "Spring"
    ],
    "jobExperience": "经验不限",
    "daysPerWeekDesc": "",
    "leastMonthDesc": "",
    "jobDegree": "本科",
    "cityName": "杭州",
    "areaDistrict": "滨江区",
    "businessDistrict": "长河",
    "jobType": 0,
    "proxyJob": 0,
    "proxyType": 0,
    "anonymous": 0,
    "outland": 0,
    "optimal": 0,
    "iconFlagList": [],
    "itemId": 50,
    "city": 101210100,
    "isShield": 0,
    "atsDirectPost": false,
    "gps": null,
    "encryptBrandId": "1fcb005b2df3d7d303J73dW4Ew~~",
    "brandName": "华为终端有限公司",
    "brandLogo": "https://img.bosszhipin.com/beijin/upload/com/logo/20210316/73ea6807f43915a26ed9cc2674429bae3e8741717a4ad566bdbc95a3b8d77bcb.png",
    "brandStageName": "不需要融资",
    "brandIndustry": "通信/网络设备",
    "brandScaleName": "10000人以上",
    "welfareList": [
        "年终奖",
        "股票期权",
        "通讯补贴",
        "带薪年假",
        "补充医疗保险",
        "员工旅游",
        "节日福利",
        "住房补贴",
        "零食下午茶",
        "加班补助",
        "五险一金",
        "定期体检",
        "免费班车",
        "交通补助"
    ],
    "industry": 100024,
    "contact": false,
    "showTopPosition": false
}