{
    "securityId": "JFOK-nl0Ztcna-D12k8d70VuWlJlSZTpmGXuwd1IqL8QNLVm_QRqrAVr--BmCes7Lhw0bWY2JBPqOUZvT2lBE1sO3I-d502AWj0sihRWpErmFQFzKjpXF3Xj_w95nxt-uMkpYmg5qiSNNQ~~",
    "bossAvatar": "https://img.bosszhipin.com/beijin/upload/avatar/20240925/607f1f3d68754fd056659210571f8e0ea2f0c120a20b5ce20d2c23792dc6eb4df617f64884a18997_s.png.webp",
    "bossCert": 3,
    "encryptBossId": "b7a118a71c764bb90nR63tq1FFZR",
    "bossName": "郑铭华",
    "bossTitle": "招聘主管",
    "goldHunter": 0,
    "bossOnline": false,
    "encryptJobId": "f86422216e972ca11H1609W8GFRW",
    "expectId": 1030426395,
    "jobName": "有源天线测试工程师",
    "lid": "2aqazaWXCHd.search.285",
    "salaryDesc": "8-13K·14薪",
    "jobLabels": [
        "1-3年",
        "本科"
    ],
    "jobValidStatus": 1,
    "iconWord": "",
    "skills": [
        "通信相关专业",
        "天线测试"
    ],
    "jobExperience": "1-3年",
    "daysPerWeekDesc": "",
    "leastMonthDesc": "",
    "jobDegree": "本科",
    "cityName": "武汉",
    "areaDistrict": "江夏区",
    "businessDistrict": "流芳",
    "jobType": 0,
    "proxyJob": 0,
    "proxyType": 0,
    "anonymous": 0,
    "outland": 0,
    "optimal": 0,
    "iconFlagList": [],
    "itemId": 285,
    "city": 101200100,
    "isShield": 0,
    "atsDirectPost": false,
    "gps": {
        "longitude": 114.444978,
        "latitude": 30.417991
    },
    "encryptBrandId": "26fe3e2bef2aeb2f1n193NW9Ew~~",
    "brandName": "通宇通讯",
    "brandLogo": "https://img.bosszhipin.com/beijin/mcs/chatphoto/20180809/4e6ea2f2f5729f14f605c5adb6d33858cfcd208495d565ef66e7dff9f98764da.jpg",
    "brandStageName": "已上市",
    "brandIndustry": "通信/网络设备",
    "brandScaleName": "1000-9999人",
    "welfareList": [
        "年终奖",
        "五险一金",
        "绩效奖金",
        "交通补助",
        "团建聚餐",
        "高温补贴",
        "通讯补贴",
        "带薪年假",
        "股票期权",
        "宿舍有空调",
        "员工旅游",
        "节日福利",
        "定期体检",
        "全勤奖",
        "工龄奖"
    ],
    "industry": 101402,
    "contact": false,
    "showTopPosition": false
}