{
    "securityId": "SGpesEK0ftrBH-o19IX4ujRgpKPthFdRHXYLjxI6VvVpF9fdERmRJi7KkV7mqKcqxtwWTZZ2uv6AdIpkjzwvBkWn3Mzdw_eA7O7VC0UIDdifiCzhEq9O",
    "bossAvatar": "https://img.bosszhipin.com/beijin/upload/avatar/20240811/607f1f3d68754fd033e8ecb117e44d0b99eef3f456e58760c1d6b445deb029c69b4100e8c2639382_s.png.webp",
    "bossCert": 3,
    "encryptBossId": "9f7f9fe2eeed76e40nJ63NS0GVRX",
    "bossName": "朱女士",
    "bossTitle": "主管",
    "goldHunter": 0,
    "bossOnline": false,
    "encryptJobId": "42da6eddbebc973b1Hd42tS6EFNX",
    "expectId": 0,
    "jobName": "小学数学老师",
    "lid": "7BukmzMfErB.search.30",
    "salaryDesc": "2-7K",
    "jobLabels": [
        "1-3年",
        "本科"
    ],
    "jobValidStatus": 1,
    "iconWord": "",
    "skills": [
        "教师资格证",
        "教师",
        "大学",
        "教育工作经验",
        "小班教学（3-25人）",
        "培训机构",
        "线下教育",
        "兼职",
        "不坐班",
        "三级教师",
        "二级甲等",
        "小学"
    ],
    "jobExperience": "1-3年",
    "daysPerWeekDesc": "",
    "leastMonthDesc": "",
    "jobDegree": "本科",
    "cityName": "武汉",
    "areaDistrict": "江夏区",
    "businessDistrict": "关山",
    "jobType": 0,
    "proxyJob": 0,
    "proxyType": 0,
    "anonymous": 0,
    "outland": 0,
    "optimal": 0,
    "iconFlagList": [],
    "itemId": 30,
    "city": 101200100,
    "isShield": 0,
    "atsDirectPost": false,
    "gps": null,
    "encryptBrandId": "126026cfc8c26c691Xd739-6EFE~",
    "brandName": "溪田教育",
    "brandLogo": "https://img.bosszhipin.com/beijin/icon/894ce6fa7e58d64d57e7f22d2f3a9d18afa7fcceaa24b8ea28f56f1bb14732c0.png",
    "brandStageName": "",
    "brandIndustry": "培训/辅导机构",
    "brandScaleName": "0-20人",
    "welfareList": [],
    "industry": 100303,
    "contact": false,
    "showTopPosition": false
}