{
    "securityId": "BJGYA6n5pAvKm-c1HkoopZH6SlTSbJvESNC537KT-Mxjjm_bBo5maiEtlE_SnAR6zpUxKuzeXcIrHyqPmgDznhzmgthTuXvhHN_bfAz_H1H-QJY7McE~",
    "bossAvatar": "https://img.bosszhipin.com/boss/avatar/avatar_7.png",
    "bossCert": 3,
    "encryptBossId": "13db2c062da5deba0nR_3N--ElRX",
    "bossName": "聂先生",
    "bossTitle": "招聘者",
    "goldHunter": 0,
    "bossOnline": false,
    "encryptJobId": "d832318082c6f0071HJ90ti9ElBX",
    "expectId": 0,
    "jobName": "软件开发助理",
    "lid": "1tNijX8j7S.search.114",
    "salaryDesc": "5-7K",
    "jobLabels": [
        "1-3年",
        "本科"
    ],
    "jobValidStatus": 1,
    "iconWord": "",
    "skills": [
        "不接受居家办公",
        "Java",
        "Python",
        "Tomcat",
        "Nginx",
        "MySQL",
        "大数据经验"
    ],
    "jobExperience": "1-3年",
    "daysPerWeekDesc": "",
    "leastMonthDesc": "",
    "jobDegree": "本科",
    "cityName": "北京",
    "areaDistrict": "昌平区",
    "businessDistrict": "回龙观",
    "jobType": 0,
    "proxyJob": 0,
    "proxyType": 0,
    "anonymous": 0,
    "outland": 0,
    "optimal": 0,
    "iconFlagList": [],
    "itemId": 114,
    "city": 101010100,
    "isShield": 0,
    "atsDirectPost": false,
    "gps": null,
    "encryptBrandId": "e572fb6c377c05591XR_2d-8EA~~",
    "brandName": "华夏佳讯",
    "brandLogo": "https://img.bosszhipin.com/beijin/icon/894ce6fa7e58d64d57e7f22d2f3a9d18afa7fcceaa24b8ea28f56f1bb14732c0.png",
    "brandStageName": "未融资",
    "brandIndustry": "移动互联网",
    "brandScaleName": "0-20人",
    "welfareList": [
        "五险一金"
    ],
    "industry": 100019,
    "contact": false,
    "showTopPosition": false
}