{
    "securityId": "noiOsULe8jRhf-F1P8QFg6nrEDikbYwA6YnavcevXlvb9wAmfcvms9MvciZssVbMFqdsso0krKyDREVhey7InBe5AuoA_LM_4ST6OXzHgAVCyEvgULs_",
    "bossAvatar": "https://img.bosszhipin.com/boss/avatar/avatar_6.png",
    "bossCert": 3,
    "encryptBossId": "f8a9405bca1ba7840XZ42dm0FVRR",
    "bossName": "何女士",
    "bossTitle": "人事",
    "goldHunter": 0,
    "bossOnline": false,
    "encryptJobId": "3d0e289f8ac27b571HZ-3du5EFVX",
    "expectId": 0,
    "jobName": "游戏数据分析",
    "lid": "aKO7393PX34.search.266",
    "salaryDesc": "8-13K",
    "jobLabels": [
        "1-3年",
        "本科"
    ],
    "jobValidStatus": 1,
    "iconWord": "",
    "skills": [
        "投放数据分析",
        "统计/数学相关专业"
    ],
    "jobExperience": "1-3年",
    "daysPerWeekDesc": "",
    "leastMonthDesc": "",
    "jobDegree": "本科",
    "cityName": "北京",
    "areaDistrict": "朝阳区",
    "businessDistrict": "亚运村",
    "jobType": 0,
    "proxyJob": 0,
    "proxyType": 0,
    "anonymous": 0,
    "outland": 0,
    "optimal": 0,
    "iconFlagList": [],
    "itemId": 266,
    "city": 101010100,
    "isShield": 0,
    "atsDirectPost": false,
    "gps": null,
    "encryptBrandId": "b4e50aa94bd2c05a1HRy2NW9ElY~",
    "brandName": "赛达互动",
    "brandLogo": "https://img.bosszhipin.com/beijin/upload/com/workfeel/20240103/7bf6f160950405e98736c0050584c450bc78e770fe5b7d3cd933ef002bf09a8a62be09a8929b25f2.png.webp",
    "brandStageName": "不需要融资",
    "brandIndustry": "游戏",
    "brandScaleName": "20-99人",
    "welfareList": [
        "五险一金",
        "定期体检",
        "零食下午茶",
        "住房补贴"
    ],
    "industry": 100002,
    "contact": false,
    "showTopPosition": false
}