{
    "securityId": "_iQhss0Vy56mK-D1QwtG0eay5bJ_pDwocQNH6ftQ2Pm3e5EPnAqNspIKaJ61N6IFtWEoI5ZJqACbWd_fkBdhc2H7pKRtPad1ZyosN6hyz-yxm6v-",
    "bossAvatar": "https://img.bosszhipin.com/beijin/mcs/useravatar/20190418/0a02d8cbbd202e52aed26bc34990c8fde5ca79fa3664dfd4205dcd4f30d1dd8a_s.png",
    "bossCert": 3,
    "encryptBossId": "dfae1acbfdc8d32803J-3NW_EVQ~",
    "bossName": "李先生",
    "bossTitle": "人事专员",
    "goldHunter": 0,
    "bossOnline": false,
    "encryptJobId": "4cc102253b5a4b921HJ62N26GFVX",
    "expectId": 0,
    "jobName": "海外游戏推广",
    "lid": "5Ey7qo8lxp2.search.208",
    "salaryDesc": "4-9K",
    "jobLabels": [
        "1-3年",
        "大专"
    ],
    "jobValidStatus": 1,
    "iconWord": "",
    "skills": [
        "游戏营销经验",
        "游戏销售",
        "玩家拉新",
        "用户拉新经验"
    ],
    "jobExperience": "1-3年",
    "daysPerWeekDesc": "",
    "leastMonthDesc": "",
    "jobDegree": "大专",
    "cityName": "长沙",
    "areaDistrict": "天心区",
    "businessDistrict": "书院路",
    "jobType": 0,
    "proxyJob": 0,
    "proxyType": 0,
    "anonymous": 0,
    "outland": 0,
    "optimal": 0,
    "iconFlagList": [],
    "itemId": 208,
    "city": 101250100,
    "isShield": 0,
    "atsDirectPost": false,
    "gps": {
        "longitude": 112.96799,
        "latitude": 28.165523
    },
    "encryptBrandId": "24681195bdaa89180nZ93NW8",
    "brandName": "E-Jade",
    "brandLogo": "https://img.bosszhipin.com/beijin/upload/com/workfeel/20210611/1115a703619bc8ee089006e4a0cd7de6a6324c85447a6b1c8695385ea47c44ae.jpg",
    "brandStageName": "不需要融资",
    "brandIndustry": "游戏",
    "brandScaleName": "100-499人",
    "welfareList": [
        "员工旅游",
        "生日礼物",
        "带薪年假",
        "五险一金",
        "节日福利",
        "生日福利",
        "定期体检",
        "零食下午茶"
    ],
    "industry": 100002,
    "contact": false,
    "showTopPosition": false
}