{
    "securityId": "VjtTLcbGrBBRx-U1NnTf9pDff61DoWYhvw7ORQK3cYgj0NUpgA9IVzjP0HMnPOaKGlK69bw6CiVuhc14P_8frI5TA-mV_MisHO-WlY9d6njJRO4mVV2g",
    "bossAvatar": "https://img.bosszhipin.com/boss/avatar/avatar_6.png",
    "bossCert": 3,
    "encryptBossId": "139640dbd5ffd2d90XV52t-8ElJZ",
    "bossName": "刘先生",
    "bossTitle": "招聘者",
    "goldHunter": 0,
    "bossOnline": false,
    "encryptJobId": "8d870025b8da4e991HB_0tW7F1tV",
    "expectId": 0,
    "jobName": "golang研发工程师",
    "lid": "9g3jmaXVNaX.search.76",
    "salaryDesc": "6-11K",
    "jobLabels": [
        "经验不限",
        "本科"
    ],
    "jobValidStatus": 1,
    "iconWord": "",
    "skills": [
        "Golang",
        "Gin",
        "Docker",
        "计算机相关专业",
        "Golang服务端开发经验",
        "211高校",
        "985高校"
    ],
    "jobExperience": "经验不限",
    "daysPerWeekDesc": "",
    "leastMonthDesc": "",
    "jobDegree": "本科",
    "cityName": "苏州",
    "areaDistrict": "苏州工业园区",
    "businessDistrict": "独墅湖",
    "jobType": 0,
    "proxyJob": 0,
    "proxyType": 0,
    "anonymous": 0,
    "outland": 0,
    "optimal": 0,
    "iconFlagList": [],
    "itemId": 76,
    "city": 101190400,
    "isShield": 0,
    "atsDirectPost": false,
    "gps": null,
    "encryptBrandId": "73ac050d7f96c9681X142dm6FVM~",
    "brandName": "苏州云畅信息科技",
    "brandLogo": "https://img.bosszhipin.com/beijin/app/mobile/normal-0e3f1e4441a21d4874cece3a3d81f0fe.png",
    "brandStageName": "",
    "brandIndustry": "互联网",
    "brandScaleName": "20-99人",
    "welfareList": [],
    "industry": 100020,
    "contact": false,
    "showTopPosition": false
}