{
    "securityId": "lOpQMl_uBNpou-b1NwzqX_HC8GaJYqhTx9GqHAkl-6pXrk_-cIiZXow0RFxlsV3zoZY225O8fAOye6Chd4SBVlN7RER-C6GLP6evel9fYBanscvMdso~",
    "bossAvatar": "https://img.bosszhipin.com/boss/avatar/avatar_8.png",
    "bossCert": 3,
    "encryptBossId": "f52463fde4223e710nZz2dm5ElpZ",
    "bossName": "张先生",
    "bossTitle": "技术总监",
    "goldHunter": 0,
    "bossOnline": false,
    "encryptJobId": "0de6b73ef16747571nF729q0EVpT",
    "expectId": 0,
    "jobName": "数据分析师",
    "lid": "8PrTjCTTLGd.search.41",
    "salaryDesc": "6-10K",
    "jobLabels": [
        "1-3年",
        "本科"
    ],
    "jobValidStatus": 1,
    "iconWord": "",
    "skills": [
        "Python",
        "SQL",
        "R语言",
        "SAS",
        "SPSS"
    ],
    "jobExperience": "1-3年",
    "daysPerWeekDesc": "",
    "leastMonthDesc": "",
    "jobDegree": "本科",
    "cityName": "杭州",
    "areaDistrict": "余杭区",
    "businessDistrict": "五常",
    "jobType": 0,
    "proxyJob": 0,
    "proxyType": 0,
    "anonymous": 0,
    "outland": 0,
    "optimal": 0,
    "iconFlagList": [],
    "itemId": 41,
    "city": 101210100,
    "isShield": 0,
    "atsDirectPost": false,
    "gps": null,
    "encryptBrandId": "cd2d25be8eaf65cd3nB42ty1Eg~~",
    "brandName": "金钻",
    "brandLogo": "https://img.bosszhipin.com/beijin/icon/894ce6fa7e58d64d57e7f22d2f3a9d18afa7fcceaa24b8ea28f56f1bb14732c0.png",
    "brandStageName": "未融资",
    "brandIndustry": "计算机软件",
    "brandScaleName": "20-99人",
    "welfareList": [
        "五险一金"
    ],
    "industry": 100021,
    "contact": false,
    "showTopPosition": false
}