{
    "securityId": "MufSW8nyVSVPI-y1_OV_mg243OAGEPvQJKbfNx02gsE05Bt3JF0A_ud4pC5rbiNCxi1DgHPYdD3LZezjS7iT_a_Oou796ixM3U8SvPbLjrM-ektF",
    "bossAvatar": "https://img.bosszhipin.com/beijin/mcs/useravatar/20190521/ff40e32e4c188af11324d16d531d05f3de3ffef2adfcd6a04b9ced2dc1ab1a93_s.jpg",
    "bossCert": 3,
    "encryptBossId": "203a38dbf471221e0Xd53dy4EFQ~",
    "bossName": "芮先生",
    "bossTitle": "经理",
    "goldHunter": 0,
    "bossOnline": false,
    "encryptJobId": "07254cdaa4b8a23b0HB72Nq4E1M~",
    "expectId": 0,
    "jobName": "苏之坊招聘供应链专员",
    "lid": "8tnyDI8KyJU.search.148",
    "salaryDesc": "4-8K",
    "jobLabels": [
        "经验不限",
        "大专"
    ],
    "jobValidStatus": 1,
    "iconWord": "",
    "skills": [
        "中大型供应链管理经验",
        "电商行业经验",
        "数据分析能力",
        "供应链专员",
        "供应链管理"
    ],
    "jobExperience": "经验不限",
    "daysPerWeekDesc": "",
    "leastMonthDesc": "",
    "jobDegree": "大专",
    "cityName": "南京",
    "areaDistrict": "溧水区",
    "businessDistrict": "永阳",
    "jobType": 0,
    "proxyJob": 0,
    "proxyType": 0,
    "anonymous": 0,
    "outland": 0,
    "optimal": 0,
    "iconFlagList": [],
    "itemId": 148,
    "city": 101190100,
    "isShield": 0,
    "atsDirectPost": false,
    "gps": null,
    "encryptBrandId": "f84b2a4453894fed03F529y-EQ~~",
    "brandName": "苏之坊",
    "brandLogo": "https://img.bosszhipin.com/beijin/upload/com/logo/20190521/ff40e32e4c188af11324d16d531d05f3de3ffef2adfcd6a04b9ced2dc1ab1a93.jpg",
    "brandStageName": "不需要融资",
    "brandIndustry": "批发/零售",
    "brandScaleName": "20-99人",
    "welfareList": [
        "年终奖",
        "带薪年假",
        "餐补"
    ],
    "industry": 100503,
    "contact": false,
    "showTopPosition": false
}