{
    "securityId": "yT7LXe8xuT7wq-B1BNs47dhE4J8o9DfEwEGIjTVoAlFI58ommBczIqg_ezehPfOIeWYqr49sktpjuc0_VpWBqJ4fwxNkEqkwoX-Wtvm2tIWvvv6e0hSVY-PGid7om5K2cTIv1L3kUpB8gEHE9dPGnJGC",
    "bossAvatar": "https://img.bosszhipin.com/beijin/upload/avatar/20240730/607f1f3d68754fd034e88e5c464c3e0ab6b56a1364992c9a6ed3a8a4aaee32658ceb21118c8707d7_s.png.webp",
    "bossCert": 3,
    "encryptBossId": "ca83a7b950d4c13b0nBz39W-EFtQ",
    "bossName": "徐女士",
    "bossTitle": "HR",
    "goldHunter": 0,
    "bossOnline": true,
    "encryptJobId": "a91c9a9ecf7b43ad1HN829S0GFZX",
    "expectId": 0,
    "jobName": "游戏动画实习生",
    "lid": "fYH1bPgE2Z.search.173",
    "salaryDesc": "1-2K",
    "jobLabels": [
        "经验不限",
        "大专"
    ],
    "jobValidStatus": 1,
    "iconWord": "",
    "skills": [
        "3ds MAX",
        "不接受居家办公",
        "3D动画",
        "游戏",
        "MAYA"
    ],
    "jobExperience": "经验不限",
    "daysPerWeekDesc": "",
    "leastMonthDesc": "",
    "jobDegree": "大专",
    "cityName": "长沙",
    "areaDistrict": "岳麓区",
    "businessDistrict": "含浦",
    "jobType": 0,
    "proxyJob": 0,
    "proxyType": 0,
    "anonymous": 0,
    "outland": 0,
    "optimal": 0,
    "iconFlagList": [],
    "itemId": 173,
    "city": 101250100,
    "isShield": 0,
    "atsDirectPost": false,
    "gps": null,
    "encryptBrandId": "933e22bd1fb9cc7b1XZ92du7FFY~",
    "brandName": "巨浪犇腾",
    "brandLogo": "https://img.bosszhipin.com/beijin/upload/com/workfeel/20230627/7bf6f160950405e9ac7f6956cac31398997162b779effe8a5a8e076974616f44552896cfdf0b48f9.png",
    "brandStageName": "不需要融资",
    "brandIndustry": "游戏",
    "brandScaleName": "100-499人",
    "welfareList": [
        "全勤奖",
        "节日福利",
        "生日福利",
        "零食下午茶",
        "带薪年假",
        "绩效奖金",
        "加班补助",
        "五险一金",
        "年终奖",
        "团建聚餐"
    ],
    "industry": 100002,
    "contact": false,
    "showTopPosition": false
}